fullcoverage/__init__.py
fullcoverage/notimported.py
fullcoverage/plugin.py
fullcoverage-0.1.0.dist-info/DESCRIPTION.rst
fullcoverage-0.1.0.dist-info/METADATA
fullcoverage-0.1.0.dist-info/RECORD
fullcoverage-0.1.0.dist-info/WHEEL
fullcoverage-0.1.0.dist-info/metadata.json
fullcoverage-0.1.0.dist-info/top_level.txt
fullcoverage-0.1.0.dist-info/zip-safe
