Metadata-Version: 2.0
Name: fullcoverage
Version: 0.1.0
Summary: Cheat and get 100% test coverage
Home-page: http://git.framasoft.org/spalax/fullcoverage
Author: Louis Paternault
Author-email: spalax@gresille.org
License: GPLv3 or any later version
Platform: UNKNOWN
Classifier: Development Status :: 4 - Beta
Classifier: Environment :: Plugins
Classifier: Intended Audience :: Developers
Classifier: License :: OSI Approved :: GNU General Public License v3 or later (GPLv3+)
Classifier: Programming Language :: Python :: 3
Classifier: Programming Language :: Python :: 3 :: Only
Classifier: Programming Language :: Python :: 3.5
Classifier: Topic :: Software Development :: Testing
Requires-Dist: coverage
